flex_ai/__init__.py
flex_ai/cli.py
flex_ai/client.py
flex_ai/settings.py
flex_ai/api/__init__.py
flex_ai/api/checkpoints.py
flex_ai/api/datasets.py
flex_ai/api/endpoints.py
flex_ai/api/fine_tunes.py
flex_ai/api/models.py
flex_ai/api/tasks.py
flex_ai/common/__init__.py
flex_ai/common/classes.py
flex_ai/common/logger.py
flex_ai/data_loaders/__init__.py
flex_ai/data_loaders/files.py
flex_ai/utils/__init__.py
flex_ai/utils/conversions.py
flex_ai-0.42.dist-info/LICENSE
flex_ai-0.42.dist-info/METADATA
flex_ai-0.42.dist-info/WHEEL
flex_ai-0.42.dist-info/entry_points.txt
flex_ai-0.42.dist-info/top_level.txt
flex_ai-0.42.dist-info/RECORD
