Metadata-Version: 2.1
Name: flex_ai
Version: 0.42
Summary: Flex AI client library
Home-page: https://github.com/arielcohen4/flex_ai
Author: Ariel Cohen
Author-email: ariel042cohen@gmail.com
Classifier: Programming Language :: Python :: 3
Classifier: License :: OSI Approved :: MIT License
Classifier: Operating System :: OS Independent
Requires-Python: >=3.6
License-File: LICENSE
Requires-Dist: pydantic
Requires-Dist: requests
Requires-Dist: colorama
Requires-Dist: click
Requires-Dist: zstandard
Requires-Dist: tqdm
